evo/data_converters/resqml/__init__.py
evo/data_converters/resqml/utils.py
evo/data_converters/resqml/importer/__init__.py
evo/data_converters/resqml/importer/_attribute_converters.py
evo/data_converters/resqml/importer/_downhole_intervals_to_evo.py
evo/data_converters/resqml/importer/_grid_converter.py
evo/data_converters/resqml/importer/_surface_converter.py
evo/data_converters/resqml/importer/_time_series_converter.py
evo/data_converters/resqml/importer/_utils.py
evo/data_converters/resqml/importer/conversion_options.py
evo/data_converters/resqml/importer/resqml_to_evo.py
evo_data_converters_resqml-0.1.4.dist-info/METADATA
evo_data_converters_resqml-0.1.4.dist-info/WHEEL
evo_data_converters_resqml-0.1.4.dist-info/licenses/LICENSE.md
evo_data_converters_resqml-0.1.4.dist-info/RECORD
